MagicBaidu/__init__.py
MagicBaidu/config.py
MagicBaidu/magic_baidu.py
MagicBaidu/data/user_agents.txt
MagicBaidu-0.0.9.dist-info/METADATA
MagicBaidu-0.0.9.dist-info/RECORD
MagicBaidu-0.0.9.dist-info/WHEEL
MagicBaidu-0.0.9.dist-info/top_level.txt
